fds/__init__.py
fds/sdk/__init__.py
fds/sdk/FactSetSupplyChain/__init__.py
fds/sdk/FactSetSupplyChain/api_client.py
fds/sdk/FactSetSupplyChain/configuration.py
fds/sdk/FactSetSupplyChain/exceptions.py
fds/sdk/FactSetSupplyChain/model_utils.py
fds/sdk/FactSetSupplyChain/rest.py
fds/sdk/FactSetSupplyChain/api/__init__.py
fds/sdk/FactSetSupplyChain/api/relationships_api.py
fds/sdk/FactSetSupplyChain/apis/__init__.py
fds/sdk/FactSetSupplyChain/model/__init__.py
fds/sdk/FactSetSupplyChain/model/company_type.py
fds/sdk/FactSetSupplyChain/model/error_object.py
fds/sdk/FactSetSupplyChain/model/error_object_links.py
fds/sdk/FactSetSupplyChain/model/error_response.py
fds/sdk/FactSetSupplyChain/model/relationship_direction.py
fds/sdk/FactSetSupplyChain/model/relationship_ids.py
fds/sdk/FactSetSupplyChain/model/relationship_type.py
fds/sdk/FactSetSupplyChain/model/relationships.py
fds/sdk/FactSetSupplyChain/model/relationships_request.py
fds/sdk/FactSetSupplyChain/model/relationships_request_body.py
fds/sdk/FactSetSupplyChain/model/relationships_response.py
fds/sdk/FactSetSupplyChain/models/__init__.py
fds_sdk_factsetsupplychain-2.0.1.dist-info/licenses/LICENSE
fds_sdk_factsetsupplychain-2.0.1.dist-info/METADATA
fds_sdk_factsetsupplychain-2.0.1.dist-info/WHEEL
fds_sdk_factsetsupplychain-2.0.1.dist-info/top_level.txt
fds_sdk_factsetsupplychain-2.0.1.dist-info/RECORD
